{
    "build-runtime": true,
    "id": "io.elementary.Sdk",
    "id-platform": "io.elementary.Platform",
    "default-branch": "daily",
    "runtime-version": "3.38",
    "runtime": "org.gnome.Platform",
    "sdk": "org.gnome.Sdk",
    "sdk-extensions": [
        "org.gnome.Sdk.Debug",
        "org.gnome.Sdk.Locale",
        "org.gnome.Sdk.Docs"
    ],
    "platform-extensions": [ "org.gnome.Platform.Locale"],
    "inherit-extensions": [
        "org.freedesktop.Platform.GL",
        "org.freedesktop.Platform.VAAPI.Intel",
        "org.freedesktop.Platform.Timezones",
        "org.freedesktop.Platform.GStreamer",
        "org.freedesktop.Platform.openh264"
    ],
    "inherit-sdk-extensions": [
        "org.freedesktop.Sdk.Extension"
    ],
    "finish-args": [
        "--env=ALSA_CONFIG_DIR=/usr/share/alsa",
        "--env=ALSA_CONFIG_PATH=/usr/share/alsa/alsa-flatpak.conf",
        "--env=GI_TYPELIB_PATH=/app/lib/girepository-1.0",
        "--env=XDG_DATA_DIRS=/app/share:/usr/share:/usr/share/runtime/share:/run/host/share",
        "--sdk=io.elementary.Sdk//daily",
        "--runtime=io.elementary.Platform//daily"
    ],
    "cleanup-platform": [
        "/share/runtime/docs",
        "/include",
        "/share/aclocal",
        "/share/pkgconfig",
        "/lib/pkgconfig",
        "/share/gir-1.0",
        "/share/vala"
    ],
    "build-options" : {
        "env": {
            "PYTHON": "python3"
        }
    },
    "modules": [
         {
            "name": "icons",
            "buildsystem": "meson",
            "sources": [
                {
                    "type": "git",
                    "url": "https://github.com/elementary/icons.git",
                    "tag": "6.0.0"
                }
            ],
            "modules": [
                {
                    "name": "xcursorgen",
                    "cleanup": [ "*" ],
                    "sources": [
                        {
                            "type": "git",
                            "url": "https://gitlab.freedesktop.org/xorg/app/xcursorgen.git",
                            "tag": "xcursorgen-1.0.7"
                        }
                    ]
                }
            ]
        },
        {
            "name": "stylesheet",
            "buildsystem": "meson",
            "sources": [
                {
                    "type": "git",
                    "url": "https://github.com/elementary/stylesheet.git",
                    "tag": "6.0.0"
                }
            ],
            "modules": [
                {
                    "name": "sassc",
                    "cleanup": [ "*" ],
                    "sources": [
                        {
                            "type": "git",
                            "url": "https://github.com/sass/sassc.git",
                            "tag": "3.6.1"
                        },
                        {
                            "type": "script",
                            "dest-filename": "autogen.sh",
                            "commands": [ "autoreconf -si" ]
                        }
                    ],
                    "modules": [
                        {
                            "name": "libsass",
                            "cleanup": [ "*" ],
                            "sources": [
                                {
                                    "type": "git",
                                    "url": "https://github.com/sass/libsass.git",
                                    "tag": "3.6.4"
                                },
                                {
                                    "type": "script",
                                    "dest-filename": "autogen.sh",
                                    "commands": [ "autoreconf -si" ]
                                }
                            ]
                        }
                    ]
                }
            ]
        },
        {
            "name": "granite",
            "buildsystem": "meson",
            "sources": [
                {
                    "type": "git",
                    "url": "https://github.com/elementary/granite.git",
                    "tag": "6.1.1"
                }
            ]
        },
        {
            "name" : "libhandy",
            "buildsystem" : "meson",
            "config-opts" : [
                "-Dintrospection=enabled",
                "-Dvapi=true",
                "-Dgtk_doc=true",
                "-Dtests=false",
                "-Dexamples=false"
            ],
            "sources" : [
                {
                    "type": "git",
                    "url": "https://gitlab.gnome.org/GNOME/libhandy.git",
                    "tag": "1.2.0"
                }
            ]
        },
        {
            "name" : "appdata",
            "buildsystem" : "meson",
            "sources" : [
                {
                    "type": "dir",
                    "path": "."
                }
            ]
        }
    ]
}
